PSHA/GMM.py
PSHA/PSHALogger.py
PSHA/SSM.py
PSHA/__init__.py
PSHA-0.1.1.dist-info/LICENSE
PSHA-0.1.1.dist-info/METADATA
PSHA-0.1.1.dist-info/WHEEL
PSHA-0.1.1.dist-info/top_level.txt
PSHA-0.1.1.dist-info/RECORD
