Metadata-Version: 2.1
Name: PSHA
Version: 0.1.1
Summary: PSHA Analysis
Home-page: https://github.com/ZibraMax/PSHA
Author: Arturo Rodriguez
Author-email: davidarturo9911@hotmail.com
License: UNKNOWN
Platform: UNKNOWN
Requires-Python: >=3.6
License-File: LICENSE
Requires-Dist: numpy
Requires-Dist: matplotlib
Requires-Dist: triangle
Requires-Dist: scipy
Provides-Extra: docs
Requires-Dist: sphinx ; extra == 'docs'
Requires-Dist: m2r2 ; extra == 'docs'
Requires-Dist: furo ; extra == 'docs'
